src/axi_apb_bridge.v
module axi_apb_bridge #(
    parameter AXI_ADDR_WIDTH = 32,
    parameter AXI_DATA_WIDTH = 32,
    parameter APB_ADDR_WIDTH = 32,
    parameter APB_DATA_WIDTH = 32
)(
    // AXI Slave Interface
    input wire                          axi_aclk,
    input wire                          axi_aresetn,
    
    // AXI Write Address Channel
    input wire [AXI_ADDR_WIDTH-1:0]     axi_awaddr,
    input wire [2:0]                    axi_awprot,
    input wire                          axi_awvalid,
    output reg                          axi_awready,
    
    // AXI Write Data Channel
    input wire [AXI_DATA_WIDTH-1:0]     axi_wdata,
    input wire [(AXI_DATA_WIDTH/8)-1:0] axi_wstrb,
    input wire                          axi_wvalid,
    output reg                          axi_wready,
    
    // AXI Write Response Channel
    output reg [1:0]                    axi_bresp,
    output reg                          axi_bvalid,
    input wire                          axi_bready,
    
    // AXI Read Address Channel
    input wire [AXI_ADDR_WIDTH-1:0]     axi_araddr,
    input wire [2:0]                    axi_arprot,
    input wire                          axi_arvalid,
    output reg                          axi_arready,
    
    // AXI Read Data Channel
    output reg [AXI_DATA_WIDTH-1:0]     axi_rdata,
    output reg [1:0]                    axi_rresp,
    output reg                          axi_rvalid,
    input wire                          axi_rready,
    
    // APB Master Interface
    output reg [APB_ADDR_WIDTH-1:0]     apb_paddr,
    output reg                          apb_pwrite,
    output reg                          apb_psel,
    output reg                          apb_penable,
    output reg [APB_DATA_WIDTH-1:0]     apb_pwdata,
    input wire [APB_DATA_WIDTH-1:0]     apb_prdata,
    input wire                          apb_pready,
    input wire                          apb_pslverr
);

    // State Encoding
    localparam IDLE        = 3'b000;
    localparam WRITE_ADDR  = 3'b001;
    localparam WRITE_DATA  = 3'b010;
    localparam WRITE_RESP  = 3'b011;
    localparam READ_ADDR   = 3'b100;
    localparam READ_DATA   = 3'b101;

    // Registers for the state machine
    reg [2:0] current_state, next_state;
    reg [AXI_ADDR_WIDTH-1:0] captured_addr;
    reg [AXI_DATA_WIDTH-1:0] captured_wdata;
    reg [(AXI_DATA_WIDTH/8)-1:0] captured_wstrb;

    // Clock Enable signal (always enabled)
    // This signal doesn't disable clocking but is used for specific control logic
    reg clk_enable;

    // Sequential logic for state transition
    always @(posedge axi_aclk or negedge axi_aresetn) begin
        if (!axi_aresetn) begin
            current_state <= IDLE;
        end else begin
            current_state <= next_state;
        end
    end

    // Combinational next state logic
    always @(*) begin
        next_state = current_state; // Default assignment
        case (current_state)
            IDLE: begin
                if (axi_awvalid) next_state = WRITE_ADDR;
                else if (axi_arvalid) next_state = READ_ADDR;
            end
            WRITE_ADDR: begin
                if (axi_wvalid) next_state = WRITE_DATA;
            end
            WRITE_DATA: begin
                if (apb_pready) next_state = WRITE_RESP;
            end
            WRITE_RESP: begin
                if (axi_bready) next_state = IDLE;
            end
            READ_ADDR: begin
                if (apb_pready) next_state = READ_DATA;
            end
            READ_DATA: begin
                if (axi_rready) next_state = IDLE;
            end
            default: next_state = IDLE;
        endcase
    end

    // Output and control path logic
    always @(posedge axi_aclk or negedge axi_aresetn) begin
        if (!axi_aresetn) begin
            // Reset all outputs and internal registers
            axi_awready <= 1'b0;
            axi_wready <= 1'b0;
            axi_arready <= 1'b0;
            axi_bvalid <= 1'b0;
            axi_rvalid <= 1'b0;
            captured_addr <= 0;
            captured_wdata <= 0;
            captured_wstrb <= 0;
            apb_paddr <= 0;
            apb_pwdata <= 0;
            apb_pwrite <= 0;
            apb_psel <= 0;
            apb_penable <= 0;
            clk_enable <= 1'b0;
        end else begin
            // Default assignments for signals
            axi_awready <= 1'b0;
            axi_wready <= 1'b0;
            axi_arready <= 1'b0;
            apb_psel <= 1'b0;
            apb_penable <= 1'b0;
            clk_enable <= 1'b1; // Clock always enabled for sequential logic

            case (current_state)
                IDLE: begin
                    if (axi_awvalid) begin
                        axi_awready <= 1'b1;
                        captured_addr <= axi_awaddr;
                    end else if (axi_arvalid) begin
                        axi_arready <= 1'b1;
                        captured_addr <= axi_araddr;
                    end
                end
                WRITE_ADDR: begin
                    if (axi_wvalid) begin
                        axi_wready <= 1'b1;
                        captured_wdata <= axi_wdata;
                        captured_wstrb <= axi_wstrb;
                    end
                end
                WRITE_DATA: begin
                    apb_psel <= 1'b1;
                    apb_pwrite <= 1'b1;
                    apb_paddr <= captured_addr;
                    apb_pwdata <= captured_wdata;
                    if (apb_pready) begin
                        apb_penable <= 1'b1;
                        axi_bresp <= apb_pslverr ? 2'b10 : 2'b00;
                        axi_bvalid <= 1'b1;
                    end
                end
                WRITE_RESP: begin
                    if (axi_bready) begin
                        axi_bvalid <= 1'b0;
                    end
                end
                READ_ADDR: begin
                    apb_psel <= 1'b1;
                    apb_pwrite <= 1'b0;
                    apb_paddr <= captured_addr;
                    if (apb_pready) begin
                        apb_penable <= 1'b1;
                        axi_rresp <= apb_pslverr ? 2'b10 : 2'b00;
                        axi_rvalid <= 1'b1;
                        axi_rdata <= apb_prdata;
                    end
                end
                READ_DATA: begin
                    if (axi_rready) begin
                        axi_rvalid <= 1'b0;
                    end
                end
            endcase
        end
    end

endmodule

Verilog/axi_apb_bridge_TB.v
`timescale 1ns/1ps

module axi_apb_bridge_tb();
    // Parameters
    parameter CLK_PERIOD = 10;  // 100 MHz clock
    parameter AXI_DATA_WIDTH = 32;
    parameter AXI_ADDR_WIDTH = 32;
    parameter APB_ADDR_WIDTH = 32;
    parameter APB_DATA_WIDTH = 32;

    // Signals for AXI Interface
    reg                     axi_aclk;
    reg                     axi_aresetn;
    
    // AXI Write Address Channel
    reg [AXI_ADDR_WIDTH-1:0]    axi_awaddr;
    reg [2:0]               axi_awprot;
    reg                     axi_awvalid;
    wire                    axi_awready;
    
    // AXI Write Data Channel
    reg [AXI_DATA_WIDTH-1:0]    axi_wdata;
    reg [(AXI_DATA_WIDTH/8)-1:0] axi_wstrb;
    reg                     axi_wvalid;
    wire                    axi_wready;
    
    // AXI Write Response Channel
    wire [1:0]              axi_bresp;
    wire                    axi_bvalid;
    reg                     axi_bready;
    
    // AXI Read Address Channel
    reg [AXI_ADDR_WIDTH-1:0]    axi_araddr;
    reg [2:0]               axi_arprot;
    reg                     axi_arvalid;
    wire                    axi_arready;
    
    // AXI Read Data Channel
    wire [AXI_DATA_WIDTH-1:0]   axi_rdata;
    wire [1:0]              axi_rresp;
    wire                    axi_rvalid;
    reg                     axi_rready;
    
    // APB Master Interface
    wire [APB_ADDR_WIDTH-1:0]   apb_paddr;
    wire                    apb_pwrite;
    wire                    apb_psel;
    wire                    apb_penable;
    wire [APB_DATA_WIDTH-1:0]   apb_pwdata;
    reg [APB_DATA_WIDTH-1:0]    apb_prdata;
    reg                     apb_pready;
    reg                     apb_pslverr;

    // Instantiate Device Under Test (DUT)
    axi_apb_bridge #(
        .AXI_ADDR_WIDTH(AXI_ADDR_WIDTH),
        .AXI_DATA_WIDTH(AXI_DATA_WIDTH),
        .APB_ADDR_WIDTH(APB_ADDR_WIDTH),
        .APB_DATA_WIDTH(APB_DATA_WIDTH)
    ) dut (
        .axi_aclk(axi_aclk),
        .axi_aresetn(axi_aresetn),
        
        .axi_awaddr(axi_awaddr),
        .axi_awprot(axi_awprot),
        .axi_awvalid(axi_awvalid),
        .axi_awready(axi_awready),
        
        .axi_wdata(axi_wdata),
        .axi_wstrb(axi_wstrb),
        .axi_wvalid(axi_wvalid),
        .axi_wready(axi_wready),
        
        .axi_bresp(axi_bresp),
        .axi_bvalid(axi_bvalid),
        .axi_bready(axi_bready),
        
        .axi_araddr(axi_araddr),
        .axi_arprot(axi_arprot),
        .axi_arvalid(axi_arvalid),
        .axi_arready(axi_arready),
        
        .axi_rdata(axi_rdata),
        .axi_rresp(axi_rresp),
        .axi_rvalid(axi_rvalid),
        .axi_rready(axi_rready),
        
        .apb_paddr(apb_paddr),
        .apb_pwrite(apb_pwrite),
        .apb_psel(apb_psel),
        .apb_penable(apb_penable),
        .apb_pwdata(apb_pwdata),
        .apb_prdata(apb_prdata),
        .apb_pready(apb_pready),
        .apb_pslverr(apb_pslverr)
    );

    // Clock generation
    always begin
        #(CLK_PERIOD/2) axi_aclk = ~axi_aclk;
    end

    // Test sequence
    initial begin
        // Initialize all signals
        axi_aclk = 0;
        axi_aresetn = 0;
        axi_awaddr = 0;
        axi_awprot = 0;
        axi_awvalid = 0;
        axi_wdata = 0;
        axi_wstrb = 0;
        axi_wvalid = 0;
        axi_bready = 0;
        axi_araddr = 0;
        axi_arprot = 0;
        axi_arvalid = 0;
        axi_rready = 0;
        
        apb_prdata = 0;
        apb_pready = 0;
        apb_pslverr = 0;

        // Reset sequence
        #(CLK_PERIOD * 2);
        axi_aresetn = 1;

        // Test 1: Write Transaction
        @(posedge axi_aclk);
        // Write address phase
        axi_awaddr = 32'h1000_0000;
        axi_awvalid = 1;
        axi_awprot = 3'b000;
        axi_bready = 1;

        @(posedge axi_aclk);
        // Write data phase
        axi_wdata = 32'hDEAD_BEEF;
        axi_wstrb = 4'hF;  // Write all bytes
        axi_wvalid = 1;

        // Simulate APB ready
        @(posedge axi_aclk);
        apb_pready = 1;

        // Wait for write response
        repeat(2) @(posedge axi_aclk);
        
        // Reset write signals
        axi_awvalid = 0;
        axi_wvalid = 0;
        apb_pready = 0;

        // Test 2: Read Transaction
        @(posedge axi_aclk);
        // Read address phase
        axi_araddr = 32'h2000_0004;
        axi_arvalid = 1;
        axi_arprot = 3'b001;
        axi_rready = 1;

        @(posedge axi_aclk);
        // Simulate APB read data
        apb_prdata = 32'h1234_5678;
        apb_pready = 1;

        // Wait for read data
        repeat(2) @(posedge axi_aclk);

        // Test 3: Error Scenario
        @(posedge axi_aclk);
        axi_awaddr = 32'h3000_0000;
        axi_awvalid = 1;
        apb_pslverr = 1;  // Simulate slave error

        // End simulation
        #(CLK_PERIOD * 10);
        $finish;
    end

    // Waveform dumping for simulation
    initial begin
        $dumpfile("axi_apb_bridge_tb.vcd");
        $dumpvars(0, axi_apb_bridge_tb);
    end

    // Timeout mechanism
    initial begin
        #(CLK_PERIOD * 100);
        $display("ERROR: Simulation timeout");
        $finish;
    end

    // Assertions and checks
    always @(posedge axi_aclk) begin
        // Check write transaction
        if (axi_awvalid && axi_awready) begin
            $display("Write Address Transaction: ADDR = %h", axi_awaddr);
        end

        // Check read transaction
        if (axi_arvalid && axi_arready) begin
            $display("Read Address Transaction: ADDR = %h", axi_araddr);
        end

        // Check read data
        if (axi_rvalid && axi_rready) begin
            $display("Read Data Transaction: DATA = %h, RESP = %b", 
                     axi_rdata, axi_rresp);
        end
    end
endmodule

Physical_Design/RTL/axi_apb_bridge_tb.vcd
$date
	Thu Nov 28 22:35:40 2024
$end
$version
	Icarus Verilog
$end
$timescale
	1ps
$end
$scope module axi_apb_bridge_tb $end
$var wire 1 ! axi_wready $end
$var wire 1 " axi_rvalid $end
$var wire 2 # axi_rresp [1:0] $end
$var wire 32 $ axi_rdata [31:0] $end
$var wire 1 % axi_bvalid $end
$var wire 2 & axi_bresp [1:0] $end
$var wire 1 ' axi_awready $end
$var wire 1 ( axi_arready $end
$var wire 1 ) apb_pwrite $end
$var wire 32 * apb_pwdata [31:0] $end
$var wire 1 + apb_psel $end
$var wire 1 , apb_penable $end
$var wire 32 - apb_paddr [31:0] $end
$var reg 32 . apb_prdata [31:0] $end
$var reg 1 / apb_pready $end
$var reg 1 0 apb_pslverr $end
$var reg 1 1 axi_aclk $end
$var reg 32 2 axi_araddr [31:0] $end
$var reg 1 3 axi_aresetn $end
$var reg 3 4 axi_arprot [2:0] $end
$var reg 1 5 axi_arvalid $end
$var reg 32 6 axi_awaddr [31:0] $end
$var reg 3 7 axi_awprot [2:0] $end
$var reg 1 8 axi_awvalid $end
$var reg 1 9 axi_bready $end
$var reg 1 : axi_rready $end
$var reg 32 ; axi_wdata [31:0] $end
$var reg 4 < axi_wstrb [3:0] $end
$var reg 1 = axi_wvalid $end
$scope module dut $end
$var wire 32 > apb_prdata [31:0] $end
$var wire 1 / apb_pready $end
$var wire 1 0 apb_pslverr $end
$var wire 1 1 axi_aclk $end
$var wire 32 ? axi_araddr [31:0] $end
$var wire 1 3 axi_aresetn $end
$var wire 3 @ axi_arprot [2:0] $end
$var wire 1 5 axi_arvalid $end
$var wire 32 A axi_awaddr [31:0] $end
$var wire 3 B axi_awprot [2:0] $end
$var wire 1 8 axi_awvalid $end
$var wire 1 9 axi_bready $end
$var wire 1 : axi_rready $end
$var wire 32 C axi_wdata [31:0] $end
$var wire 4 D axi_wstrb [3:0] $end
$var wire 1 = axi_wvalid $end
$var reg 32 E apb_paddr [31:0] $end
$var reg 1 , apb_penable $end
$var reg 1 + apb_psel $end
$var reg 32 F apb_pwdata [31:0] $end
$var reg 1 ) apb_pwrite $end
$var reg 1 ( axi_arready $end
$var reg 1 ' axi_awready $end
$var reg 2 G axi_bresp [1:0] $end
$var reg 1 % axi_bvalid $end
$var reg 32 H axi_rdata [31:0] $end
$var reg 2 I axi_rresp [1:0] $end
$var reg 1 " axi_rvalid $end
$var reg 1 ! axi_wready $end
$var reg 32 J captured_addr [31:0] $end
$var reg 32 K captured_wdata [31:0] $end
$var reg 4 L captured_wstrb [3:0] $end
$var reg 1 M clk_enable $end
$var reg 3 N current_state [2:0] $end
$var reg 3 O next_state [2:0] $end
$upscope $end
$upscope $end
$enddefinitions $end
#0
$dumpvars
b0 O
b0 N
0M
b0 L
b0 K
b0 J
bx I
bx H
bx G
b0 F
b0 E
b0 D
b0 C
b0 B
b0 A
b0 @
b0 ?
b0 >
0=
b0 <
b0 ;
0:
09
08
b0 7
b0 6
05
b0 4
03
b0 2
01
00
0/
b0 .
b0 -
0,
0+
b0 *
0)
0(
0'
bx &
0%
bx $
bx #
0"
0!
$end
#5000
11
#10000
01
#15000
11
#20000
01
13
#25000
b10000000000000000000000000000 J
1'
1M
b1 O
19
18
b10000000000000000000000000000 6
b10000000000000000000000000000 A
11
#30000
01
#35000
b1 N
1'
b10 O
1=
b1111 <
b1111 D
b11011110101011011011111011101111 ;
b11011110101011011011111011101111 C
11
#40000
01
#45000
b1111 L
b11011110101011011011111011101111 K
1!
0'
b10 N
b11 O
1/
11
#50000
01
#55000
b0 O
b11 N
1%
b0 &
b0 G
1,
b11011110101011011011111011101111 *
b11011110101011011011111011101111 F
b10000000000000000000000000000 -
b10000000000000000000000000000 E
1)
1+
0!
11
#60000
01
#65000
0%
0,
0+
b0 N
b0 O
0/
0=
08
11
#70000
01
#75000
b100000000000000000000000000100 J
1(
b100 O
1:
b1 4
b1 @
15
b100000000000000000000000000100 2
b100000000000000000000000000100 ?
11
#80000
01
#85000
1(
b100 N
b101 O
1/
b10010001101000101011001111000 .
b10010001101000101011001111000 >
11
#90000
01
#95000
b0 O
b101 N
b10010001101000101011001111000 $
b10010001101000101011001111000 H
1"
b0 #
b0 I
1,
b100000000000000000000000000100 -
b100000000000000000000000000100 E
0)
1+
0(
11
#100000
01
#105000
b100 O
0"
0,
0+
b0 N
11
#110000
01
#115000
b100 N
b110000000000000000000000000000 J
1'
b101 O
10
18
b110000000000000000000000000000 6
b110000000000000000000000000000 A
11
#120000
01
#125000
b0 O
1"
b10 #
b10 I
1,
b110000000000000000000000000000 -
b110000000000000000000000000000 E
1+
0'
b101 N
11
#130000
01
#135000
b1 O
b0 N
0"
0,
0+
11
#140000
01
#145000
1'
b1 N
11
#150000
01
#155000
0'
11
